odoo/addons/account_chart_update/README.rst
odoo/addons/account_chart_update/__init__.py
odoo/addons/account_chart_update/__manifest__.py
odoo/addons/account_chart_update/i18n/account_chart_update.pot
odoo/addons/account_chart_update/i18n/am.po
odoo/addons/account_chart_update/i18n/ar.po
odoo/addons/account_chart_update/i18n/bg.po
odoo/addons/account_chart_update/i18n/bs.po
odoo/addons/account_chart_update/i18n/ca.po
odoo/addons/account_chart_update/i18n/ca_ES.po
odoo/addons/account_chart_update/i18n/cs.po
odoo/addons/account_chart_update/i18n/da.po
odoo/addons/account_chart_update/i18n/de.po
odoo/addons/account_chart_update/i18n/el_GR.po
odoo/addons/account_chart_update/i18n/en_GB.po
odoo/addons/account_chart_update/i18n/es.po
odoo/addons/account_chart_update/i18n/es_AR.po
odoo/addons/account_chart_update/i18n/es_CL.po
odoo/addons/account_chart_update/i18n/es_CO.po
odoo/addons/account_chart_update/i18n/es_CR.po
odoo/addons/account_chart_update/i18n/es_DO.po
odoo/addons/account_chart_update/i18n/es_EC.po
odoo/addons/account_chart_update/i18n/es_ES.po
odoo/addons/account_chart_update/i18n/es_MX.po
odoo/addons/account_chart_update/i18n/es_PE.po
odoo/addons/account_chart_update/i18n/es_PY.po
odoo/addons/account_chart_update/i18n/es_VE.po
odoo/addons/account_chart_update/i18n/et.po
odoo/addons/account_chart_update/i18n/eu.po
odoo/addons/account_chart_update/i18n/fa.po
odoo/addons/account_chart_update/i18n/fi.po
odoo/addons/account_chart_update/i18n/fr.po
odoo/addons/account_chart_update/i18n/fr_CA.po
odoo/addons/account_chart_update/i18n/fr_CH.po
odoo/addons/account_chart_update/i18n/gl.po
odoo/addons/account_chart_update/i18n/gl_ES.po
odoo/addons/account_chart_update/i18n/gu.po
odoo/addons/account_chart_update/i18n/he.po
odoo/addons/account_chart_update/i18n/hr.po
odoo/addons/account_chart_update/i18n/hr_HR.po
odoo/addons/account_chart_update/i18n/hu.po
odoo/addons/account_chart_update/i18n/id.po
odoo/addons/account_chart_update/i18n/it.po
odoo13_addon_account_chart_update-13.0.2.0.1.dist-info/METADATA
odoo13_addon_account_chart_update-13.0.2.0.1.dist-info/WHEEL
odoo13_addon_account_chart_update-13.0.2.0.1.dist-info/top_level.txt
odoo13_addon_account_chart_update-13.0.2.0.1.dist-info/RECORD
