Metadata-Version: 2.1
Name: odoo13-addon-account-chart-update
Version: 13.0.2.0.1
Summary: Wizard to update a company's account chart from a template
Home-page: https://github.com/OCA/account-financial-tools
Author: Tecnativa, BCIM, Okia, Odoo Community Association (OCA)
Author-email: support@odoo-community.org
License: AGPL-3
Platform: UNKNOWN
Classifier: Programming Language :: Python
Classifier: Framework :: Odoo
Classifier: Framework :: Odoo :: 13.0
Classifier: License :: OSI Approved :: GNU Affero General Public License v3
Requires-Python: >=3.5
Requires-Dist: odoo (<13.1dev,>=13.0a)
